{
  "version": "5.1",
  "generated_at": "2026-06-25T07:21:29.327846+00:00",
  "directive": {
    "system_objective_today": "DEFENSE_HARDENING",
    "posture": "OFFENSIVE",
    "market_mode": "ATTACK",
    "target_market_exposure_pct": 0.85,
    "max_sector_concentration_pct": 0.4,
    "max_position_concentration_pct": 0.15,
    "volatility_budget_pct": 0.05,
    "deployment_pacing": "deploy_fast",
    "recycling_cadence_hours": 8,
    "account_priority_order": [
      "HARVEST_3",
      "HARVEST_5",
      "LEGACY"
    ]
  },
  "current_state": {
    "system_equity": 29926.0,
    "system_deployed_ratio": 0.1247,
    "system_sgov_ratio": 0.0,
    "system_idle_ratio": 0.8753,
    "active_regimes": [
      "narrow_leadership"
    ],
    "force_rotations_queued": 0,
    "watch_positions": 2,
    "violation_flags": [],
    "regime_stability": 1.0
  },
  "sector_targets": {
    "Health Care": {
      "target_pct": 0.1226,
      "current_pct": 0.0,
      "gap": 0.1226,
      "action": "add",
      "flow_score": 0.2948
    },
    "Staples": {
      "target_pct": 0.0737,
      "current_pct": 0.0,
      "gap": 0.0737,
      "action": "add",
      "flow_score": -0.0885
    },
    "Commodities": {
      "target_pct": 0.0404,
      "current_pct": 0.0,
      "gap": 0.0404,
      "action": "add_slow",
      "flow_score": -0.35
    },
    "Technology": {
      "target_pct": 0.0,
      "current_pct": 0.0,
      "gap": 0.0,
      "action": "hold",
      "flow_score": -0.7662
    },
    "Communication": {
      "target_pct": 0.0404,
      "current_pct": 0.0,
      "gap": 0.0404,
      "action": "add_slow",
      "flow_score": -0.35
    },
    "Communication Services": {
      "target_pct": 0.0873,
      "current_pct": 0.0,
      "gap": 0.0873,
      "action": "add",
      "flow_score": 0.018
    },
    "Consumer Discretionary": {
      "target_pct": 0.052,
      "current_pct": 0.0,
      "gap": 0.052,
      "action": "add",
      "flow_score": -0.2587
    },
    "Rates": {
      "target_pct": 0.0702,
      "current_pct": 0.0,
      "gap": 0.0702,
      "action": "add",
      "flow_score": -0.1161
    },
    "Token": {
      "target_pct": 0.1296,
      "current_pct": 0.0,
      "gap": 0.1296,
      "action": "add",
      "flow_score": 0.35
    },
    "Software": {
      "target_pct": 0.0404,
      "current_pct": 0.0,
      "gap": 0.0404,
      "action": "add_slow",
      "flow_score": -0.35
    },
    "Crypto": {
      "target_pct": 0.0404,
      "current_pct": 0.0,
      "gap": 0.0404,
      "action": "add_slow",
      "flow_score": -0.35
    },
    "Index": {
      "target_pct": 0.0585,
      "current_pct": 0.0,
      "gap": 0.0585,
      "action": "add",
      "flow_score": -0.2082
    },
    "Innovation": {
      "target_pct": 0.048,
      "current_pct": 0.0,
      "gap": 0.048,
      "action": "add_slow",
      "flow_score": -0.29
    },
    "Energy": {
      "target_pct": 0.0404,
      "current_pct": 0.0,
      "gap": 0.0404,
      "action": "add_slow",
      "flow_score": -0.35
    },
    "Consumer Staples": {
      "target_pct": 0.118,
      "current_pct": 0.0,
      "gap": 0.118,
      "action": "add",
      "flow_score": 0.2587
    },
    "Healthcare": {
      "target_pct": 0.082,
      "current_pct": 0.0213,
      "gap": 0.0607,
      "action": "add",
      "flow_score": -0.0237
    },
    "Communications": {
      "target_pct": 0.0404,
      "current_pct": 0.0,
      "gap": 0.0404,
      "action": "add_slow",
      "flow_score": -0.35
    },
    "Discretionary": {
      "target_pct": 0.0773,
      "current_pct": 0.1034,
      "gap": -0.0261,
      "action": "trim_slow",
      "flow_score": -0.0605
    },
    "Credit": {
      "target_pct": 0.065,
      "current_pct": 0.0,
      "gap": 0.065,
      "action": "add",
      "flow_score": -0.1572
    },
    "Real Estate": {
      "target_pct": 0.0477,
      "current_pct": 0.0,
      "gap": 0.0477,
      "action": "add_slow",
      "flow_score": -0.2925
    },
    "Materials": {
      "target_pct": 0.106,
      "current_pct": 0.0,
      "gap": 0.106,
      "action": "add",
      "flow_score": 0.1647
    },
    "Industrials": {
      "target_pct": 0.0794,
      "current_pct": 0.0,
      "gap": 0.0794,
      "action": "add",
      "flow_score": -0.0439
    },
    "Semiconductors": {
      "target_pct": 0.0658,
      "current_pct": 0.0,
      "gap": 0.0658,
      "action": "add",
      "flow_score": -0.1507
    },
    "Financials": {
      "target_pct": 0.1005,
      "current_pct": 0.0,
      "gap": 0.1005,
      "action": "add",
      "flow_score": 0.1216
    },
    "Utilities": {
      "target_pct": 0.104,
      "current_pct": 0.0,
      "gap": 0.104,
      "action": "add",
      "flow_score": 0.1493
    },
    "FX": {
      "target_pct": 0.0508,
      "current_pct": 0.0,
      "gap": 0.0508,
      "action": "add",
      "flow_score": -0.2685
    }
  },
  "rationale": "objective=DEFENSE_HARDENING \u00b7 posture=OFFENSIVE \u00b7 exposure target 85%"
}